imgur_python/Account.py
imgur_python/Album.py
imgur_python/Authorize.py
imgur_python/Comment.py
imgur_python/Exceptions.py
imgur_python/FileCheck.py
imgur_python/Gallery.py
imgur_python/Image.py
imgur_python/Imgur.py
imgur_python/ImgurBase.py
imgur_python/__init__.py
imgur_python-0.2.4.dist-info/LICENSE
imgur_python-0.2.4.dist-info/METADATA
imgur_python-0.2.4.dist-info/WHEEL
imgur_python-0.2.4.dist-info/top_level.txt
imgur_python-0.2.4.dist-info/RECORD
