Metadata-Version: 2.1
Name: imgur-python
Version: 0.2.4
Summary: A Python client for the Imgur API
Home-page: https://faustocarrera.github.io/imgur-python/
Author: Fausto Carrera
Author-email: fausto.carrera@gmx.com
License: GPLv3+
Download-URL: https://github.com/faustocarrera/imgur-python
Platform: any
Classifier: Development Status :: 4 - Beta
Classifier: Environment :: Web Environment
Classifier: Intended Audience :: Developers
Classifier: Operating System :: OS Independent
Classifier: Programming Language :: Python
Classifier: Topic :: Software Development :: Libraries :: Python Modules
Classifier: License :: OSI Approved :: GNU General Public License (GPL)
Requires-Python: >=3.1
Requires-Dist: requests (>=2.0)
Requires-Dist: fleep (>=1.0)
